signalfx_gcf/__init__.py
signalfx_gcf/utils.py
signalfx_gcf/version.py
signalfx_gcf/serverless/__init__.py
signalfx_gcf/serverless/metrics.py
signalfx_gcf/serverless/tracing.py
signalfx_gcf/serverless/utils.py
signalfx_serverless_gcf-0.0.1.dist-info/LICENSE
signalfx_serverless_gcf-0.0.1.dist-info/METADATA
signalfx_serverless_gcf-0.0.1.dist-info/WHEEL
signalfx_serverless_gcf-0.0.1.dist-info/top_level.txt
signalfx_serverless_gcf-0.0.1.dist-info/zip-safe
signalfx_serverless_gcf-0.0.1.dist-info/RECORD
